networkx_mermaid/__init__.py
networkx_mermaid/builders.py
networkx_mermaid/formatters.py
networkx_mermaid/models.py
networkx_mermaid/typing.py
networkx_mermaid-0.2.1.dist-info/METADATA
networkx_mermaid-0.2.1.dist-info/WHEEL
networkx_mermaid-0.2.1.dist-info/licenses/LICENSE
networkx_mermaid-0.2.1.dist-info/RECORD
