Metadata-Version: 2.4
Name: networkx-mermaid
Version: 0.2.1
Summary: Create a Mermaid graph from a NetworkX graph
Project-URL: Homepage, https://github.com/erivlis/networkx-mermaid
Project-URL: Documentation, https://github.com/erivlis/networkx-mermaid
Project-URL: Bug Tracker, https://github.com/erivlis/networkx-mermaid/issues
Project-URL: Source, https://github.com/erivlis/networkx-mermaid
Author-email: Eran Rivlis <eran@rivlis.info>
License-File: LICENSE
Keywords: Graph,Mermaid,NetworkX
Classifier: Development Status :: 3 - Alpha
Classifier: Intended Audience :: Developers
Classifier: Intended Audience :: Information Technology
Classifier: Intended Audience :: Science/Research
Classifier: License :: OSI Approved :: MIT License
Classifier: Natural Language :: English
Classifier: Operating System :: OS Independent
Classifier: Programming Language :: Python :: 3
Classifier: Programming Language :: Python :: 3 :: Only
Classifier: Programming Language :: Python :: 3.10
Classifier: Programming Language :: Python :: 3.11
Classifier: Programming Language :: Python :: 3.12
Classifier: Programming Language :: Python :: 3.13
Classifier: Programming Language :: Python :: Implementation :: CPython
Classifier: Topic :: Scientific/Engineering
Classifier: Topic :: Software Development :: Libraries
Classifier: Typing :: Typed
Requires-Python: >=3.10
Requires-Dist: mappingtools>=0.4.0
Requires-Dist: networkx>=3.4.2
